tracepooling/TraceLayer.py
tracepooling/__init__.py
tracepooling_layer/TraceLayer.py
tracepooling_layer/__init__.py
tracepooling-0.1.dist-info/LICENSE
tracepooling-0.1.dist-info/METADATA
tracepooling-0.1.dist-info/WHEEL
tracepooling-0.1.dist-info/top_level.txt
tracepooling-0.1.dist-info/RECORD
