Metadata-Version: 2.1
Name: tracepooling
Version: 0.1
Summary: A package to implement trace pooling layer
Home-page: https://github.com/spatUV/tracepooling/
Author: Irene Martin
Author-email: irene.martin@uv.es
License: UNKNOWN
Platform: UNKNOWN
Classifier: Programming Language :: Python :: 3.7
Classifier: License :: OSI Approved :: GNU General Public License v3 (GPLv3)
Requires-Dist: tensorflow (>=1)
